ansys/aedt/toolkits/networkEditor/pyaedt_network.py
ansys/aedt/toolkits/networkEditor/assets/bootstrap.css
ansys/aedt/toolkits/networkEditor/assets/check_closing.js
ansys/aedt/toolkits/networkEditor/assets/dashAgGridFunctions.js
icepak_network_deps-1.0.0.dist-info/METADATA
icepak_network_deps-1.0.0.dist-info/WHEEL
icepak_network_deps-1.0.0.dist-info/top_level.txt
icepak_network_deps-1.0.0.dist-info/RECORD
