Metadata-Version: 2.1
Name: icepak-network-deps
Version: 1.0.0
Summary: Toolkit to visualize Icepak Network Editor
Author-email: Kiran Gavini <kiran.gavini@ansys.com>, Deven Bibikar <dbibikar@berkeley.edu>
Project-URL: Homepage, https://github.com/ansys
Classifier: Programming Language :: Python :: 3
Classifier: License :: OSI Approved :: MIT License
Classifier: Operating System :: OS Independent
Requires-Python: >=3.8
